bitmart/__init__.py
bitmart/__version__.py
bitmart/api_account.py
bitmart/api_broker.py
bitmart/api_contract.py
bitmart/api_margin_loan.py
bitmart/api_spot.py
bitmart/api_system.py
bitmart/lib/__init__.py
bitmart/lib/cloud_client.py
bitmart/lib/cloud_consts.py
bitmart/lib/cloud_exceptions.py
bitmart/lib/cloud_log.py
bitmart/lib/cloud_utils.py
bitmart/websocket/__init__.py
bitmart/websocket/futures_socket_client.py
bitmart/websocket/socket_manager.py
bitmart/websocket/spot_socket_client.py
bitmart_python_sdk_api-2.5.0.dist-info/licenses/LICENSE.md
bitmart_python_sdk_api-2.5.0.dist-info/METADATA
bitmart_python_sdk_api-2.5.0.dist-info/WHEEL
bitmart_python_sdk_api-2.5.0.dist-info/top_level.txt
bitmart_python_sdk_api-2.5.0.dist-info/RECORD
