Metadata-Version: 2.4
Name: bitmart-python-sdk-api
Version: 2.5.0
Summary: BitMart Exchange official(https://bitmart.com) Python client for the BitMart Cloud API
Home-page: https://github.com/bitmartexchange/bitmart-python-sdk-api
License: MIT
Keywords: BitMart Exchange,BitMart API,BitMart Websocket
Classifier: Intended Audience :: Developers
Classifier: Intended Audience :: Financial and Insurance Industry
Classifier: License :: OSI Approved :: MIT License
Classifier: Programming Language :: Python :: 3.7
Classifier: Programming Language :: Python :: 3.8
Classifier: Programming Language :: Python :: 3.9
Classifier: Programming Language :: Python :: 3.10
Requires-Python: >=3.7
License-File: LICENSE.md
Requires-Dist: requests>=2.25.1
Requires-Dist: websocket-client>=1.6.3
Dynamic: classifier
Dynamic: description
Dynamic: description-content-type
Dynamic: home-page
Dynamic: keywords
Dynamic: license
Dynamic: license-file
Dynamic: requires-dist
Dynamic: requires-python
Dynamic: summary
